momcodwiz/__init__.py
momcodwiz/generator.py
momcodwiz-7.7.8.dist-info/METADATA
momcodwiz-7.7.8.dist-info/WHEEL
momcodwiz-7.7.8.dist-info/top_level.txt
momcodwiz-7.7.8.dist-info/RECORD
