Metadata-Version: 2.4
Name: momcodwiz
Version: 7.7.8
Classifier: Programming Language :: Python :: 3
Classifier: License :: OSI Approved :: MIT License
Classifier: Operating System :: OS Independent
Requires-Python: >=3.8
Dynamic: classifier
Dynamic: description
Dynamic: description-content-type
Dynamic: requires-python
